MANIFEST.in
README.rst
setup.py
ez/__init__.py
ez/ez.py
ez/prepublish.py
ez/version.py
ez.egg-info/PKG-INFO
ez.egg-info/SOURCES.txt
ez.egg-info/dependency_links.txt
ez.egg-info/requires.txt
ez.egg-info/top_level.txt