Metadata-Version: 2.1
Name: ez
Version: 11.5.8
Summary: easy stuff
Home-page: https://pypi.python.org/pypi/ez
Author: Jerry Zhu
Author-email: jerryzhujian9@gmail.com
License: GPLv3+
Keywords: shell,cross-platform,easy,wrapper
Classifier: Development Status :: 3 - Alpha
Classifier: Intended Audience :: Developers
Classifier: Topic :: Software Development :: Build Tools
Classifier: License :: OSI Approved :: GNU General Public License v3 or later (GPLv3+)
Classifier: Programming Language :: Python :: 2.7
Classifier: Programming Language :: Python :: 3.11
